Metadata-Version: 2.1
Name: ngits-users
Version: 2.0.0
Summary: Base users application for Django projects
Home-page: https://ngits.dev
Author: NGITs
License: BSD-3-Clause
Classifier: Environment :: Web Environment
Classifier: Framework :: Django
Classifier: Framework :: Django :: 5.0
Classifier: Intended Audience :: Developers
Classifier: License :: OSI Approved :: BSD License
Classifier: Operating System :: OS Independent
Classifier: Programming Language :: Python :: 3.11
Classifier: Topic :: Internet :: WWW/HTTP
Classifier: Topic :: Internet :: WWW/HTTP :: Dynamic Content
Requires-Python: >=3.11
Requires-Dist: Django==5.*
Requires-Dist: djangorestframework==3.*
Requires-Dist: drf-spectacular==0.27.*
Requires-Dist: requests==2.*
Requires-Dist: celery==5.*
Requires-Dist: redis==5.*
